calculator8/__init__.py
calculator8/button_names.py
calculator8/calculator.py
calculator8/calculator_date.py
calculator8/calculator_date_page.py
calculator8/calculator_page.py
calculator8/calculator_standard_science.py
calculator8/programmer_page.py
calculator8/science_page.py
calculator8/standard_page.py
calculator8-2.0.0.dist-info/LICENSE
calculator8-2.0.0.dist-info/METADATA
calculator8-2.0.0.dist-info/WHEEL
calculator8-2.0.0.dist-info/top_level.txt
calculator8-2.0.0.dist-info/RECORD
